django_comments_tree/__init__.py
django_comments_tree/abstract.py
django_comments_tree/admin.py
django_comments_tree/apps.py
django_comments_tree/compat.py
django_comments_tree/forms.py
django_comments_tree/models.py
django_comments_tree/moderation.py
django_comments_tree/signals.py
django_comments_tree/signed.py
django_comments_tree/urls.py
django_comments_tree/utils.py
django_comments_tree/views.py
django_comments_tree/api/__init__.py
django_comments_tree/api/frontend.py
django_comments_tree/api/serializers.py
django_comments_tree/api/views.py
django_comments_tree/conf/__init__.py
django_comments_tree/conf/defaults.py
django_comments_tree/locale/es/LC_MESSAGES/django.po
django_comments_tree/locale/es/LC_MESSAGES/djangojs.po
django_comments_tree/locale/fi/LC_MESSAGES/django.po
django_comments_tree/locale/fi/LC_MESSAGES/djangojs.po
django_comments_tree/locale/fr/LC_MESSAGES/django.po
django_comments_tree/locale/fr/LC_MESSAGES/djangojs.po
django_comments_tree/management/__init__.py
django_comments_tree/management/commands/__init__.py
django_comments_tree/management/commands/populate_tree_comments.py
django_comments_tree/migrations/0001_initial.py
django_comments_tree/migrations/__init__.py
django_comments_tree/static/django_comments_tree/css/_bootswatch.scss
django_comments_tree/static/django_comments_tree/css/_variables.scss
django_comments_tree/static/django_comments_tree/css/bootstrap.css
django_comments_tree/static/django_comments_tree/css/bootstrap.min.css
django_comments_tree/static/django_comments_tree/fonts/glyphicons-halflings-regular.eot
django_comments_tree/static/django_comments_tree/fonts/glyphicons-halflings-regular.svg
django_comments_tree/static/django_comments_tree/fonts/glyphicons-halflings-regular.ttf
django_comments_tree/static/django_comments_tree/fonts/glyphicons-halflings-regular.woff
django_comments_tree/static/django_comments_tree/fonts/glyphicons-halflings-regular.woff2
django_comments_tree/static/django_comments_tree/img/64x64.svg
django_comments_tree-0.1.0a0.dev0.dist-info/AUTHORS
django_comments_tree-0.1.0a0.dev0.dist-info/LICENSE
django_comments_tree-0.1.0a0.dev0.dist-info/METADATA
django_comments_tree-0.1.0a0.dev0.dist-info/WHEEL
django_comments_tree-0.1.0a0.dev0.dist-info/top_level.txt
django_comments_tree-0.1.0a0.dev0.dist-info/zip-safe
django_comments_tree-0.1.0a0.dev0.dist-info/RECORD
