Metadata-Version: 2.1
Name: django-comments-tree
Version: 0.1.0a0.dev0
Summary: Django Comments Framework extension app with django-treebeard support, follow up notifications and email confirmations, as well as real-time comments using Firebase for notifications.
Home-page: http://pypi.python.org/pypi/django-comments-tree
Author: Ed Henderson
Author-email: ed@sharpertool.com
Maintainer: Ed Henderson
Maintainer-email: ed@sharpertool.com
License: MIT
Keywords: django comments treebeard threaded firebase
Platform: UNKNOWN
Classifier: Development Status :: 5 - Production/Stable
Classifier: Environment :: Web Environment
Classifier: Intended Audience :: Developers
Classifier: License :: OSI Approved :: MIT License
Classifier: Operating System :: OS Independent
Classifier: Programming Language :: Python
Classifier: Programming Language :: Python :: 3
Classifier: Framework :: Django
Classifier: Natural Language :: English
Classifier: Topic :: Internet :: WWW/HTTP :: Dynamic Content :: News/Diary
Requires-Dist: Django (>=2.0)
Requires-Dist: django-treebeard (>=4.1.0)
Requires-Dist: django-contrib-comments (>=1.8)
Requires-Dist: djangorestframework (>=3.6)
Requires-Dist: docutils
Requires-Dist: six
